Workbook

Sheet Read Me
A1: Cognitive Bias Trainer — Content Database
A3: This workbook is the content backbone for a Duolingo-style app that teaches cognitive biases through quizzes.
A5: Sheet 1 — Bias Library: the master list of biases (one row per bias). Everything else references bias_id.
A6: Sheet 2 — Challenge Library: the quiz questions. Each row is one multiple-choice challenge linked to a bias_id.
A7: Sheet 3 — Categories: the lookup list used to filter/tag biases and contexts.
A8: Sheet 4 — Bias Statistics: auto-calculated counts (formulas, not hardcoded) showing how many challenges exist per bias, and the breakdown by difficulty.
A10: Current coverage: 20 biases x 3 challenges each = 60 challenges, spread across Recognition / Application / Ambiguous difficulty, and across real-world contexts (Politics, Work, Finance, Health, Media, Relationships, Social Media, Sport, Everyday life...).
A12: Each challenge includes: statement, 4 options, correct answer, explanation, a reflection question, why humans do this, real-world context, difficulty, and a Learning Objective — so every question teaches a thinking habit, not just a vocabulary term.
A14: To grow this later: duplicate a row in Challenge Library, give it a new challenge_id, set the same bias_id, and fill in new content (by hand or AI-generated). Bias Statistics will update automatically.

Sheet Bias Library
A1: bias_id | B1: Bias | C1: Definition | D1: Category | E1: Description | F1: Everyday Tip | G1: Common Contexts
A2: B001 | B2: Confirmation Bias | C2: We tend to search for, interpret, and recall information that confirms our existing beliefs. | D2: Decision Making | E2: Confirmation bias leads people to favor information that supports what they already think, while ignoring or downplaying evidence that contradicts it. | F2: Before forming an opinion, actively seek out one source that disagrees with you. | G2: Politics, Investing, Relationships, News, Health, Social Media
A3: B002 | B3: Anchoring Bias | C3: We rely too heavily on the first piece of information offered (the 'anchor') when making decisions. | D3: Decision Making | E3: Once an anchor is set, later judgments are made by adjusting away from it, but the adjustment is usually insufficient. | F3: When negotiating, try to set your own reference point first instead of reacting to the other side's opening number. | G3: Negotiation, Shopping, Salary discussions, Real estate, Everyday life
A4: B003 | B4: Availability Heuristic | C4: We judge the likelihood of events based on how easily examples come to mind. | D4: Decision Making | E4: Vivid, recent, or emotionally charged events are recalled more easily, so we overestimate how common they are. | F4: Check statistics instead of relying on memorable stories when estimating risk. | G4: Media, Health, Safety, Everyday life, News
A5: B004 | B5: Fundamental Attribution Error | C5: We judge others' behavior as caused by their character, while excusing our own behavior as caused by circumstances. | D5: Social Judgement | E5: When explaining someone else's actions we overweight personality traits and underweight situational factors, but we do the opposite for ourselves. | F5: Before judging someone's behavior, ask what situational pressures might explain it. | G5: Work, Relationships, Driving, Social situations
A6: B005 | B6: Self-serving Bias | C6: We attribute our successes to our own abilities and our failures to external circumstances. | D6: Social Judgement | E6: This bias protects self-esteem by crediting ourselves for good outcomes while blaming outside factors for bad ones. | F6: When something goes wrong, ask honestly what part, if any, was within your control. | G6: Work, Sport, Academics, Relationships
A7: B006 | B7: Sunk Cost Fallacy | C7: We continue investing in something because of what we've already invested, rather than evaluating future value. | D7: Finance | E7: Past costs (time, money, effort) that cannot be recovered still influence decisions, even though only future costs and benefits should matter. | F7: Ask: 'if I hadn't invested anything yet, would I still choose to start this today?' | G7: Finance, Relationships, Work, Everyday life
A8: B007 | B8: Negativity Bias | C8: We give more psychological weight to negative experiences than to positive ones of equal intensity. | D8: Emotion | E8: Bad events, criticism, or emotions tend to have a bigger impact on our mood, memory, and decisions than good ones. | F8: When reviewing feedback, deliberately count the positive points as well as the negative ones. | G8: Work, Relationships, Media, Self-awareness
A9: B008 | B9: Halo Effect | C9: Our overall impression of a person influences how we judge their specific traits, so one positive trait makes us assume other positive traits. | D9: Social Judgement | E9: If someone is attractive, likeable, or competent in one area, we tend to assume they're good in unrelated areas too. | F9: Evaluate people's specific skills and claims separately from your overall impression of them. | G9: Work, Media, Social situations, Politics
A10: B009 | B10: Horn Effect | C10: One negative trait about a person leads us to assume other negative traits, the opposite of the halo effect. | D10: Social Judgement | E10: A single flaw or bad first impression can unfairly color our judgment of someone's other, unrelated qualities. | F10: When you notice a negative first impression, pause and check if you're generalizing unfairly. | G10: Work, Social situations, Media
A11: B010 | B11: Survivorship Bias | C11: We focus on the people or things that 'survived' a process, while overlooking those that didn't, skewing our conclusions. | D11: Decision Making | E11: Because failures are often invisible or unreported, we draw conclusions from an incomplete, success-only sample. | F11: When hearing a success story, actively ask how many people tried the same thing and failed. | G11: Work, Media, Finance, Learning
A12: B011 | B12: Hindsight Bias | C12: After an event happens, we tend to believe we 'knew it all along,' even if we couldn't have predicted it beforehand. | D12: Decision Making | E12: Once we know the outcome, our memory of our own earlier predictions shifts to seem more accurate than they really were. | F12: Write predictions down beforehand so you can honestly check them against what you actually said. | G12: Finance, Sport, Politics, Work
... A21: B020 | B21: Authority Bias | C21: We tend to attribute greater accuracy and trust to the opinions of an authority figure, regardless of the actual content. | D21: Social Judgement | E21: A person's title, uniform, or perceived status can make their claims seem more credible, even without supporting evidence. | F21: Evaluate a claim by its evidence, then separately consider whether the source's authority is actually relevant to that claim. | G21: Work, Health, Media, Politics

Sheet Challenge Library
A1: challenge_id | B1: bias_id | C1: Bias | D1: Statement | E1: Option A | F1: Option B | G1: Option C | H1: Option D | I1: Correct Answer | J1: Explanation | K1: Reflection Question | L1: Why Humans Do This | M1: Real World Context | N1: Difficulty | O1: Learning Objective
A2: C001 | B2: B001 | C2: Confirmation Bias | D2: I only read news that agrees with what I already believe — the rest feels untrustworthy. | E2: Halo Effect | F2: Confirmation Bias | G2: Anchoring Bias | H2: Availability Heuristic | I2: B | J2: Sources get dismissed for disagreeing, not because they're wrong. | K2: When did you last listen to a view you disagreed with — on purpose? | L2: We lean toward what fits what we already think. It feels safer and easier — but it can narrow what we're willing to hear. | M2: Politics | N2: Recognition | O2: Learn that seeking confirming evidence feels natural but can limit better decisions.
A3: C002 | B3: B001 | C3: Confirmation Bias | D3: After I bought a stock, I only followed analysts who said it would rise — and ignored warnings about debt. | E3: Anchoring Bias | F3: Availability Heuristic | G3: Halo Effect | H3: Confirmation Bias | I3: D | J3: After deciding, only the good news gets noticed. | K3: After you decide something, do you look for doubts — or proof you were right? | L3: Once we've committed, we want to feel we made the right call. Doubt is uncomfortable — so we often skip it. | M3: Investing | N3: Application | O3: Learn to actively look for disconfirming evidence after making decisions, not just before.
A4: C003 | B4: B001 | C4: Confirmation Bias | D4: My feed is full of posts I agree with — so it feels like everyone thinks the same way. | E4: Halo Effect | F4: Confirmation Bias | G4: Anchoring Bias | H4: Availability Heuristic | I4: B | J4: A curated feed gets mistaken for how most people think. | K4: Does your feed challenge you, or mostly agree with you? | L4: We engage more with what we agree with. Platforms show us more of it — and the loop can feel like reality. | M4: Social Media | N4: Ambiguous | O4: Learn how confirmation bias interacts with algorithms to create feedback loops that feel like reality.
A5: C004 | B5: B002 | C5: Anchoring Bias | D5: A house is listed at $500k. Even if that's high, buyers still haggle around that number. | E5: Anchoring Bias | F5: Framing Effect | G5: Status Quo Bias | H5: Confirmation Bias | I5: A | J5: The listing price becomes the anchor for every offer. | K5: Has a first price ever shaped what felt 'fair' to you? | L5: The first number we see sticks. We adjust from there — but rarely far enough. | M5: Real Estate | N5: Recognition | O5: Learn to recognize when a starting number is shaping your judgment instead of the actual value.
A6: C005 | B6: B002 | C6: Anchoring Bias | D6: A jacket was $300, now $150 — feels like a steal, even if $150 is still a lot. | E6: Status Quo Bias | F6: Confirmation Bias | G6: Anchoring Bias | H6: Framing Effect | I6: C | J6: The old price makes the discount feel bigger than it is. | K6: Next 'sale' tag you see — what's the item actually worth? | L6: We focus on the drop, not the real value. The starting price quietly pulls our judgment. | M6: Shopping | N6: Application | O6: Learn to evaluate the actual value of something rather than the discount from an arbitrary starting price.
A7: C006 | B7: B002 | C7: Anchoring Bias | D7: In a job interview, they ask for my salary first — and that number ends up anchoring the whole negotiation. | E7: Anchoring Bias | F7: Framing Effect | G7: Status Quo Bias | H7: Confirmation Bias | I7: A | J7: The first number spoken becomes the reference for everything after. | K7: Have you ever felt stuck near a number you said early on? | L7: Early numbers are hard to let go of — even when new info suggests we should move on. | M7: Salary discussions | N7: Ambiguous | O7: Learn that anchors set early in a conversation can quietly control the entire negotiation.
A8: C007 | B8: B003 | C8: Availability Heuristic | D8: After a few plane-crash stories in the news, flying feels terrifying — even though stats say driving is riskier. | E8: Confirmation Bias | F8: Negativity Bias | G8: Survivorship Bias | H8: Availability Heuristic | I8: D | J8: Vivid stories feel more common than they are. | K8: Any fear you have that might come from memorable stories, not stats? | L8: Easy-to-recall events feel more likely. Our brain uses memory as a shortcut. | M8: News | N8: Recognition | O8: Learn that memorable events are not always common events.
A9: C008 | B9: B003 | C9: Availability Heuristic | D9: I saw one viral post about a rare vaccine side effect — and it stuck more than the disease risks I ignored. | E9: Survivorship Bias | F9: Availability Heuristic | G9: Confirmation Bias | H9: Negativity Bias | I9: B | J9: One vivid story outweighed the broader data. | K9: On health risks, do you check the data or trust the story that sticks? | L9: Emotional stories lodge in memory. Dry statistics often don't. | M9: Health | N9: Application | O9: Learn to seek base-rate statistics rather than relying on memorable anecdotes.
A10: C009 | B10: B003 | C10: Availability Heuristic | D10: After a friend's house was burgled, burglaries suddenly feel common here — even though crime has been falling. | E10: Confirmation Bias | F10: Negativity Bias | G10: Survivorship Bias | H10: Availability Heuristic | I10: D | J10: One close story outweighed the wider trend. | K10: Has one person's story ever changed how safe you feel? | L10: Stories from people we know feel real and relevant — more than numbers on a page. | M10: Everyday life | N10: Ambiguous | O10: Learn to distinguish between a personally vivid story and an actual trend.
A11: C010 | B11: B004 | C11: Fundamental Attribution Error | D11: A colleague was late to the meeting. Everyone assumed they're lazy — not knowing their car broke down. | E11: Halo Effect | F11: Horn Effect | G11: Fundamental Attribution Error | H11: Self-serving Bias | I11: C | J11: Character got blamed before circumstances were considered. | K11: Next time someone's late — what situation might explain it? | L11: We don't see others' full context, so we fill the gap with personality labels. | M11: Work | N11: Recognition | O11: Learn to consider circumstances before judging character.
A12: C011 | B12: B004 | C12: Fundamental Attribution Error | D12: Someone cut me off in traffic. I thought 'what a jerk' — without wondering if they had an emergency. | E12: Fundamental Attribution Error | F12: Self-serving Bias | G12: Halo Effect | H12: Horn Effect | I12: A | J12: The action was blamed on character, not situation. | K12: Have you ever driven badly because of your own bad day? | L12: It's faster to judge a stranger's character than imagine their unseen story. | M12: Driving | N12: Application | O12: Learn that the same behavior looks different depending on whether you know the situation behind it.
... A61: C060 | B61: B020 | C61: Authority Bias | D61: An actor who played a doctor on TV comments on real medicine — and viewers partly trust them because of the role. | E61: Framing Effect | F61: Confirmation Bias | G61: Authority Bias | H61: Halo Effect | I61: C | J61: A fictional role lent unearned credibility. | K61: Would you trust this take as much if you didn't know who was speaking? | L61: Familiarity with an authority-like role can feel like real expertise. | M61: Media | N61: Ambiguous | O61: Learn to check whether a person's actual expertise, not their perceived role, supports their claim.

Sheet Categories
A1: category_id | B1: Category
A2: CAT01 | B2: Decision Making
A3: CAT02 | B3: Social Judgement
A4: CAT03 | B4: Politics
A5: CAT04 | B5: Relationships
A6: CAT05 | B6: Work
A7: CAT06 | B7: Finance
A8: CAT07 | B8: Learning
A9: CAT08 | B9: Health
A10: CAT09 | B10: Media
A11: CAT10 | B11: Negotiation
A12: CAT11 | B12: Self-awareness
A13: CAT12 | B13: Emotion

Sheet Bias Statistics
A1: bias_id | B1: Bias | C1: Category | D1: Number of Challenges | E1: Recognition | F1: Application | G1: Ambiguous
A2: B001 | B2: Confirmation Bias | C2: Decision Making | D2: =COUNTIF('Challenge Library'!$B$2:$B$61,A2) | E2: =COUNTIFS('Challenge Library'!$B$2:$B$61,A2,'Challenge Library'!$N$2:$N$61,"Recognition") | F2: =COUNTIFS('Challenge Library'!$B$2:$B$61,A2,'Challenge Library'!$N$2:$N$61,"Application") | G2: =COUNTIFS('Challenge Library'!$B$2:$B$61,A2,'Challenge Library'!$N$2:$N$61,"Ambiguous")
A3: B002 | B3: Anchoring Bias | C3: Decision Making | D3: =COUNTIF('Challenge Library'!$B$2:$B$61,A3) | E3: =COUNTIFS('Challenge Library'!$B$2:$B$61,A3,'Challenge Library'!$N$2:$N$61,"Recognition") | F3: =COUNTIFS('Challenge Library'!$B$2:$B$61,A3,'Challenge Library'!$N$2:$N$61,"Application") | G3: =COUNTIFS('Challenge Library'!$B$2:$B$61,A3,'Challenge Library'!$N$2:$N$61,"Ambiguous")
A4: B003 | B4: Availability Heuristic | C4: Decision Making | D4: =COUNTIF('Challenge Library'!$B$2:$B$61,A4) | E4: =COUNTIFS('Challenge Library'!$B$2:$B$61,A4,'Challenge Library'!$N$2:$N$61,"Recognition") | F4: =COUNTIFS('Challenge Library'!$B$2:$B$61,A4,'Challenge Library'!$N$2:$N$61,"Application") | G4: =COUNTIFS('Challenge Library'!$B$2:$B$61,A4,'Challenge Library'!$N$2:$N$61,"Ambiguous")
A5: B004 | B5: Fundamental Attribution Error | C5: Social Judgement | D5: =COUNTIF('Challenge Library'!$B$2:$B$61,A5) | E5: =COUNTIFS('Challenge Library'!$B$2:$B$61,A5,'Challenge Library'!$N$2:$N$61,"Recognition") | F5: =COUNTIFS('Challenge Library'!$B$2:$B$61,A5,'Challenge Library'!$N$2:$N$61,"Application") | G5: =COUNTIFS('Challenge Library'!$B$2:$B$61,A5,'Challenge Library'!$N$2:$N$61,"Ambiguous")
A6: B005 | B6: Self-serving Bias | C6: Social Judgement | D6: =COUNTIF('Challenge Library'!$B$2:$B$61,A6) | E6: =COUNTIFS('Challenge Library'!$B$2:$B$61,A6,'Challenge Library'!$N$2:$N$61,"Recognition") | F6: =COUNTIFS('Challenge Library'!$B$2:$B$61,A6,'Challenge Library'!$N$2:$N$61,"Application") | G6: =COUNTIFS('Challenge Library'!$B$2:$B$61,A6,'Challenge Library'!$N$2:$N$61,"Ambiguous")
A7: B006 | B7: Sunk Cost Fallacy | C7: Finance | D7: =COUNTIF('Challenge Library'!$B$2:$B$61,A7) | E7: =COUNTIFS('Challenge Library'!$B$2:$B$61,A7,'Challenge Library'!$N$2:$N$61,"Recognition") | F7: =COUNTIFS('Challenge Library'!$B$2:$B$61,A7,'Challenge Library'!$N$2:$N$61,"Application") | G7: =COUNTIFS('Challenge Library'!$B$2:$B$61,A7,'Challenge Library'!$N$2:$N$61,"Ambiguous")
A8: B007 | B8: Negativity Bias | C8: Emotion | D8: =COUNTIF('Challenge Library'!$B$2:$B$61,A8) | E8: =COUNTIFS('Challenge Library'!$B$2:$B$61,A8,'Challenge Library'!$N$2:$N$61,"Recognition") | F8: =COUNTIFS('Challenge Library'!$B$2:$B$61,A8,'Challenge Library'!$N$2:$N$61,"Application") | G8: =COUNTIFS('Challenge Library'!$B$2:$B$61,A8,'Challenge Library'!$N$2:$N$61,"Ambiguous")
A9: B008 | B9: Halo Effect | C9: Social Judgement | D9: =COUNTIF('Challenge Library'!$B$2:$B$61,A9) | E9: =COUNTIFS('Challenge Library'!$B$2:$B$61,A9,'Challenge Library'!$N$2:$N$61,"Recognition") | F9: =COUNTIFS('Challenge Library'!$B$2:$B$61,A9,'Challenge Library'!$N$2:$N$61,"Application") | G9: =COUNTIFS('Challenge Library'!$B$2:$B$61,A9,'Challenge Library'!$N$2:$N$61,"Ambiguous")
A10: B009 | B10: Horn Effect | C10: Social Judgement | D10: =COUNTIF('Challenge Library'!$B$2:$B$61,A10) | E10: =COUNTIFS('Challenge Library'!$B$2:$B$61,A10,'Challenge Library'!$N$2:$N$61,"Recognition") | F10: =COUNTIFS('Challenge Library'!$B$2:$B$61,A10,'Challenge Library'!$N$2:$N$61,"Application") | G10: =COUNTIFS('Challenge Library'!$B$2:$B$61,A10,'Challenge Library'!$N$2:$N$61,"Ambiguous")
A11: B010 | B11: Survivorship Bias | C11: Decision Making | D11: =COUNTIF('Challenge Library'!$B$2:$B$61,A11) | E11: =COUNTIFS('Challenge Library'!$B$2:$B$61,A11,'Challenge Library'!$N$2:$N$61,"Recognition") | F11: =COUNTIFS('Challenge Library'!$B$2:$B$61,A11,'Challenge Library'!$N$2:$N$61,"Application") | G11: =COUNTIFS('Challenge Library'!$B$2:$B$61,A11,'Challenge Library'!$N$2:$N$61,"Ambiguous")
A12: B011 | B12: Hindsight Bias | C12: Decision Making | D12: =COUNTIF('Challenge Library'!$B$2:$B$61,A12) | E12: =COUNTIFS('Challenge Library'!$B$2:$B$61,A12,'Challenge Library'!$N$2:$N$61,"Recognition") | F12: =COUNTIFS('Challenge Library'!$B$2:$B$61,A12,'Challenge Library'!$N$2:$N$61,"Application") | G12: =COUNTIFS('Challenge Library'!$B$2:$B$61,A12,'Challenge Library'!$N$2:$N$61,"Ambiguous")
A13: B012 | B13: False Consensus Effect | C13: Social Judgement | D13: =COUNTIF('Challenge Library'!$B$2:$B$61,A13) | E13: =COUNTIFS('Challenge Library'!$B$2:$B$61,A13,'Challenge Library'!$N$2:$N$61,"Recognition") | F13: =COUNTIFS('Challenge Library'!$B$2:$B$61,A13,'Challenge Library'!$N$2:$N$61,"Application") | G13: =COUNTIFS('Challenge Library'!$B$2:$B$61,A13,'Challenge Library'!$N$2:$N$61,"Ambiguous")
... A21: B020 | B21: Authority Bias | C21: Social Judgement | D21: =COUNTIF('Challenge Library'!$B$2:$B$61,A21) | E21: =COUNTIFS('Challenge Library'!$B$2:$B$61,A21,'Challenge Library'!$N$2:$N$61,"Recognition") | F21: =COUNTIFS('Challenge Library'!$B$2:$B$61,A21,'Challenge Library'!$N$2:$N$61,"Application") | G21: =COUNTIFS('Challenge Library'!$B$2:$B$61,A21,'Challenge Library'!$N$2:$N$61,"Ambiguous")
A22: TOTAL | D22: =SUM(D2:D21) | E22: =SUM(E2:E21) | F22: =SUM(F2:F21) | G22: =SUM(G2:G21)
